{
  "users": [
    {
      "email": "admin@email.com",
      "password": "123456789",
      "id": 1,
      "isAdmin": true
    },
    {
      "email": "oliviera@mail.com",
      "password": "$2a$10$g1/HRNmIMurtue.UpDUTLeN4L7NgukJUgvYzGJwWKGYOYweJcxfVS",
      "id": 2
    },
    {
      "email": "senacrs@email.com",
      "password": "$2a$10$KqRwZrsTCukyhaRTZJwd9ujqRIxLp/DbXoifom5LAUzdbFAI50m2q",
      "id": 3
    }
  ],
  "produtos": [
    {
      "produtos": "TENIS ",
      "valorInicial": "80,00",
      "valorFinal": "220,00",
      "id": 16
    },
    {
      "produtos": "SAPATO SOCIAL",
      "valorInicial": "300,00",
      "valorFinal": "585,98",
      "id": 17
    },
    {
      "produtos": "SANDALIAS",
      "valorInicial": "89,64",
      "valorFinal": "219,23",
      "id": 18
    },
    {
      "produtos": "CHUTEIRA",
      "valorInicial": "100,53",
      "valorFinal": "200,24",
      "id": 19
    },
    {
      "produtos": "BOTAS",
      "valorInicial": "209,33",
      "valorFinal": "506,30",
      "id": 20
    }
   
  ]
}